Metadata-Version: 1.1
Name: cgat-daisy
Version: 0.1.9
Summary: daisy : data i-something system
Home-page: http://www.cgat.org/cgat/Tools/
Author: Andreas Heger
Author-email: andreas.heger@gmail.com
License: MIT
Keywords: computational genomics
Platform: any
Classifier: Development Status :: 3 - Alpha
Classifier: Intended Audience :: Science/Research
Classifier: Intended Audience :: Developers
Classifier: License :: OSI Approved
Classifier: Programming Language :: Python
Classifier: Topic :: Software Development
Classifier: Topic :: Scientific/Engineering
Classifier: Operating System :: POSIX
Classifier: Operating System :: Unix
Classifier: Operating System :: MacOS
